{
  "migrations": [
    {
      "version": "11.0.0-alpha.0",
      "factory": "./noop/noop.schematic",
      "description": "Update all SKY UX component packages",
      "package": "@skyux/packages",
      "name": "noop"
    },
    {
      "version": "10.8.0",
      "factory": "./update-10/remove-nx-cache/remove-nx-cache.schematic",
      "description": "Remove `.nx/cache` from git and add `.gitignore` entry.",
      "package": "@skyux/packages",
      "name": "remove-nx-cache"
    },
    {
      "version": "10.7.0",
      "factory": "./update-10/add-forms-help-inline-peer-dependency/add-forms-help-inline-peer-dependency.schematic",
      "description": "Add @skyux/help-inline peer dependency for @skyux/forms.",
      "package": "@skyux/packages",
      "name": "add-forms-help-inline-peer-dependency"
    },
    {
      "version": "10.32.0",
      "factory": "./update-10/add-indicators-help-inline-peer-dependency/add-indicators-help-inline-peer-dependency.schematic",
      "description": "Add @skyux/help-inline peer dependency for @skyux/indicators.",
      "package": "@skyux/packages",
      "name": "add-indicators-help-inline-peer-dependency"
    }
  ]
}